[
  {
    "password": "",
    "id": 1,
    "isHidden": false,
    "isFirstTimeEntering": true,
    "userId": 8397711,
    "fullName": "תום",
    "phoneNumber": "0549619631",
    "fieldsOfInterest": [
      "ניהול",
      "אבטחה"
    ]
  },
  {
    "password": "",
    "id": 2,
    "isHidden": false,
    "isFirstTimeEntering": true,
    "userId": 8350352,
    "fullName": "יהונדב איתם",
    "phoneNumber": "0545695240",
    "fieldsOfInterest": [
      "הדרכת טיולים"
    ]
  },
  {
    "password": "",
    "id": 3,
    "isHidden": false,
    "isFirstTimeEntering": true,
    "userId": 8277635,
    "fullName": "רון בכר",
    "phoneNumber": "0549549123",
    "fieldsOfInterest": [
      "חינוך מיוחד/עמותות",
      "בע\"ה בהמשך ייעוץ משפטי(סטודנט תואר שני במשפטים *לא עורך דין*)"
    ]
  },
  {
    "password": "",
    "id": 4,
    "isHidden": false,
    "isFirstTimeEntering": true,
    "userId": 7502698,
    "fullName": "עידו חבצלת ",
    "phoneNumber": "0525858546",
    "fieldsOfInterest": [
      "מסחר בשוק ההון",
      "מאמן כושר אישי אונליין"
    ]
  },
  {
    "password": "",
    "id": 5,
    "isHidden": false,
    "isFirstTimeEntering": true,
    "userId": 7612658,
    "fullName": "יעקב יודקין",
    "phoneNumber": "0523559980",
    "fieldsOfInterest": [
      "שיעורי עזר בפיזיקה (אפשר גם מתמטיקה ומחשבים עבור לא מתמטיקאים ולא מדמח)",
      "חיפוש עבודה לבעלי תאור מתקדם במקצועות הSTEM"
    ]
  },
  {
    "password": "",
    "id": 6,
    "isHidden": false,
    "isFirstTimeEntering": true,
    "userId": 6172730,
    "fullName": "שאול הורוביץ",
    "phoneNumber": "0526421278",
    "fieldsOfInterest": [
      "היי-טק",
      "real-time embedded/chip design/verification"
    ]
  },
  {
    "password": "",
    "id": 7,
    "isHidden": false,
    "isFirstTimeEntering": true,
    "userId": 8457695,
    "fullName": "ניר בנימין",
    "phoneNumber": "0528817592",
    "fieldsOfInterest": [
      "סטודנט למדעי המחשב",
      "תוכנה",
      "פיתוח",
      "דאטה"
    ]
  },
  {
    "password": "",
    "id": 8,
    "isHidden": false,
    "isFirstTimeEntering": true,
    "userId": 8536147,
    "fullName": "בנימין גורליק",
    "phoneNumber": "0529566975",
    "fieldsOfInterest": [
      "אין לי",
      "נגינה",
      "אין לי",
      "אין לי"
    ]
  },
  {
    "password": "",
    "id": 9,
    "isHidden": false,
    "isFirstTimeEntering": true,
    "userId": 5803501,
    "fullName": "תמיר חג'ג'",
    "phoneNumber": "0509001382",
    "fieldsOfInterest": [
      "בעל מחסן עץ",
      "פרגולות",
      "דקים",
      "עץ"
    ]
  },
  {
    "password": "",
    "id": 10,
    "isHidden": false,
    "isFirstTimeEntering": true,
    "userId": 5614304,
    "fullName": "מנחם קוגלמן",
    "phoneNumber": "0+1-516-849-2761",
    "fieldsOfInterest": [
      "יועץ של עסקים",
      "לימודים במנהל עסקים (MBA)",
      "עבודה ולימודים בארצות הברית",
      "טיולים בארצות הברית"
    ]
  },
  {
    "password": "",
    "id": 11,
    "isHidden": false,
    "isFirstTimeEntering": true,
    "userId": 8000787,
    "fullName": "תומר טופז",
    "phoneNumber": "0528279279",
    "fieldsOfInterest": [
      "חשמל",
      "תאורה"
    ]
  },
  {
    "password": "",
    "id": 12,
    "isHidden": false,
    "isFirstTimeEntering": true,
    "userId": 8707445,
    "fullName": "אחיה אליהו",
    "phoneNumber": "0543930110",
    "fieldsOfInterest": [
      "חינוך מיוחד",
      "בריסטה",
      "שיפוצים ובנייה"
    ]
  },
  {
    "password": "",
    "id": 13,
    "isHidden": false,
    "isFirstTimeEntering": true,
    "userId": 5394805,
    "fullName": "אייל מינצברג",
    "phoneNumber": "0523961991",
    "fieldsOfInterest": [
      "הנדסת בניין"
    ]
  },
  {
    "password": "",
    "id": 14,
    "isHidden": false,
    "isFirstTimeEntering": true,
    "userId": 6119846,
    "fullName": "יואל סטרמן",
    "phoneNumber": "0504800669",
    "fieldsOfInterest": [
      "ניהול נכסים",
      "ייצור ויבוא מזון",
      "גיוס כספים לעמותות"
    ]
  },
  {
    "password": "",
    "id": 15,
    "isHidden": false,
    "isFirstTimeEntering": true,
    "userId": 7540253,
    "fullName": "אברהם ",
    "phoneNumber": "0522724879",
    "fieldsOfInterest": [
      "אלגוריתמים בסיס ומתמטיקה בדידה",
      "מתכנת"
    ]
  },
  {
    "password": "",
    "id": 16,
    "isHidden": false,
    "isFirstTimeEntering": true,
    "userId": 6034117,
    "fullName": "בנימין נבו ",
    "phoneNumber": "0542286411",
    "fieldsOfInterest": [
      "הנדסת אלקטרוניקה"
    ]
  },
  {
    "password": "",
    "id": 17,
    "isHidden": false,
    "isFirstTimeEntering": true,
    "userId": 8237091,
    "fullName": "אופק בן שלוש ",
    "phoneNumber": "0522653780",
    "fieldsOfInterest": [
      "סטודנט שנה 3 להנדסת חשמל"
    ]
  },
  {
    "password": "",
    "id": 18,
    "isHidden": false,
    "isFirstTimeEntering": true,
    "userId": 7575904,
    "fullName": "רפאל סלמן",
    "phoneNumber": "0545568450",
    "fieldsOfInterest": [
      "ניהול רשתות ואבטחת מידע"
    ]
  },
  {
    "password": "",
    "id": 19,
    "isHidden": false,
    "isFirstTimeEntering": true,
    "userId": 8717986,
    "fullName": "אורי אסיס",
    "phoneNumber": "0533351148",
    "fieldsOfInterest": [
      "יועץ ביטוחי בתחום הבריאות החיים ומחלות קשות"
    ]
  },
  {
    "password": "",
    "id": 20,
    "isHidden": false,
    "isFirstTimeEntering": true,
    "userId": 8126909,
    "fullName": "מתן נאור",
    "phoneNumber": "0556676406",
    "fieldsOfInterest": [
      "תחום it תקשורת אבטחת מידע ומחשבים"
    ]
  },
  {
    "password": "",
    "id": 21,
    "isHidden": false,
    "isFirstTimeEntering": true,
    "userId": 8774017,
    "fullName": "זוהר אזרייב ",
    "phoneNumber": "0535213740",
    "fieldsOfInterest": [
      "ברמן במקצועי בעל ניסיון איכותי"
    ]
  },
  {
    "password": "",
    "id": 22,
    "isHidden": false,
    "isFirstTimeEntering": true,
    "userId": 7591462,
    "fullName": "שי ספז ",
    "phoneNumber": "0509333901",
    "fieldsOfInterest": [
      "נדל״ן",
      "השקעות",
      "יזמות",
      "ניהול"
    ]
  },
  {
    "password": "",
    "id": 23,
    "isHidden": false,
    "isFirstTimeEntering": true,
    "userId": 6885263,
    "fullName": "מתן אפרת ",
    "phoneNumber": "0506930075",
    "fieldsOfInterest": [
      "נגרות אומן",
      "מכירות",
      "תקשורת."
    ]
  },
  {
    "password": "",
    "id": 24,
    "isHidden": false,
    "isFirstTimeEntering": true,
    "userId": 5930445,
    "fullName": "טל שטרק",
    "phoneNumber": "0509251500",
    "fieldsOfInterest": [
      "עו״ד מקרקעין",
      "עו״ד צוואות וירושות",
      "עו״ד מוסמך יפוי כח מתמשך"
    ]
  },
  {
    "password": "",
    "id": 25,
    "isHidden": false,
    "isFirstTimeEntering": true,
    "userId": 8803859,
    "fullName": "שניר גרמנסקי",
    "phoneNumber": "0509352037",
    "fieldsOfInterest": [
      "נדלן - פיליפים השבחות ודירות יד שנייה",
      "לבעלי הון עצמי נמוך",
      "הרצאות בתחום הנדל״ן (מומלץ לצעירים בעלי הון עצמי נמוך )"
    ]
  },
  {
    "password": "",
    "id": 26,
    "isHidden": false,
    "isFirstTimeEntering": true,
    "userId": 7659296,
    "fullName": "אביב",
    "phoneNumber": "0502210190",
    "fieldsOfInterest": [
      "הנדסת תכנה"
    ]
  },
  {
    "password": "",
    "id": 27,
    "isHidden": false,
    "isFirstTimeEntering": true,
    "userId": 7556457,
    "fullName": "אריאל רוזין",
    "phoneNumber": "0524722485",
    "fieldsOfInterest": [
      "בנקאות",
      "הייטק",
      "עסקים"
    ]
  },
  {
    "password": "",
    "id": 28,
    "isHidden": false,
    "isFirstTimeEntering": true,
    "userId": 8329862,
    "fullName": "עדן וינר",
    "phoneNumber": "0526724884",
    "fieldsOfInterest": [
      "אני מחפש משרת סטודנט בתחום מדעי המחשב"
    ]
  },
  {
    "password": "",
    "id": 29,
    "isHidden": false,
    "isFirstTimeEntering": true,
    "userId": 8559295,
    "fullName": "איתן שטרן",
    "phoneNumber": "0058-5996677 ",
    "fieldsOfInterest": [
      "מסגור רשתות / סורגים",
      "ניהול פרוייקטים בניה ושיפוצים"
    ]
  },
  {
    "password": "",
    "id": 30,
    "isHidden": false,
    "isFirstTimeEntering": true,
    "userId": 9308529,
    "fullName": "יוסף נדל",
    "phoneNumber": "0584392743",
    "fieldsOfInterest": [
      "סטודנט בקוגניציה ומנהל עסקים בעברית",
      "הסמכה לרבנות",
      "מנהל מחנה בחול",
      "יש לי הרבה חברים בארצות הברית"
    ]
  },
  {
    "password": "",
    "id": 31,
    "isHidden": false,
    "isFirstTimeEntering": true,
    "userId": 5772328,
    "fullName": "מתן בלום",
    "phoneNumber": "0545830736",
    "fieldsOfInterest": [
      "פיתוח אתרים",
      "שיווק",
      "אי-קומרס",
      "Ux up designer and social marketing"
    ]
  },
  {
    "password": "",
    "id": 32,
    "isHidden": false,
    "isFirstTimeEntering": true,
    "userId": 8568949,
    "fullName": "אוראל בשיר",
    "phoneNumber": "0528832868",
    "fieldsOfInterest": [
      "Data analyst",
      "fraud analyst",
      "information systems"
    ]
  },
  {
    "password": "",
    "id": 33,
    "isHidden": false,
    "isFirstTimeEntering": true,
    "userId": 4748805,
    "fullName": "מיכאל בסוס",
    "phoneNumber": "0545578822",
    "fieldsOfInterest": [
      "פרוייקטים חברתיים וחינוכיים"
    ]
  },
  {
    "password": "",
    "id": 34,
    "isHidden": false,
    "isFirstTimeEntering": true,
    "userId": 6025084,
    "fullName": "יצחק כהן צמח ",
    "phoneNumber": "0504595360",
    "fieldsOfInterest": [
      "גיוס משאבים ותרומות"
    ]
  },
  {
    "password": "",
    "id": 35,
    "isHidden": false,
    "isFirstTimeEntering": true,
    "userId": 7659383,
    "fullName": "נתנאל נגר",
    "phoneNumber": "0527056596",
    "fieldsOfInterest": [
      "הנדסאי בניין",
      "עוזר בטיחות",
      "עוזר מנהל פרוייקטים"
    ]
  },
  {
    "password": "",
    "id": 36,
    "isHidden": false,
    "isFirstTimeEntering": true,
    "userId": 8388790,
    "fullName": "ולדיסלב שרדיקו",
    "phoneNumber": "0525875456",
    "fieldsOfInterest": [
      "פיתוח אתרים"
    ]
  }
]